relations_psycopg2.py
relations_psycopg2-0.6.9.dist-info/LICENSE.txt
relations_psycopg2-0.6.9.dist-info/METADATA
relations_psycopg2-0.6.9.dist-info/WHEEL
relations_psycopg2-0.6.9.dist-info/top_level.txt
relations_psycopg2-0.6.9.dist-info/RECORD
