Metadata-Version: 2.1
Name: relations-psycopg2
Version: 0.6.9
Summary: DB Modeling for PostgreSQL using the psycopg2 library
Home-page: https://github.com/relations-dil/python-relations-psycopg2
Author: Gaffer Fitch
Author-email: relations@gaf3.com
Classifier: Programming Language :: Python :: 3
Classifier: License :: OSI Approved :: MIT License
License-File: LICENSE.txt
Requires-Dist: psycopg2 (==2.8.6)
Requires-Dist: relations-dil (>=0.6.12)
Requires-Dist: relations-postgresql (>=0.6.2)
